greekwordnet/__init__.py
greekwordnet/greekwordnet.py
greekwordnet-0.0.7.dist-info/METADATA
greekwordnet-0.0.7.dist-info/WHEEL
greekwordnet-0.0.7.dist-info/top_level.txt
greekwordnet-0.0.7.dist-info/RECORD
