Metadata-Version: 2.1
Name: greekwordnet
Version: 0.0.7
Summary: A light-weight Python wrapper for the Greek WordNet API
Home-page: https://greekwordnet.chs.harvard.edu
Author: William Michael Short
Author-email: w.short@exeter.ac.uk
License: GNU General Public License v3.0
Platform: UNKNOWN
Requires-Dist: requests (>=2.22.0)
Requires-Dist: python-dotenv (>=0.12.0)
